{
  "url": "https://www.islamicity.org/news",
  "contentType": "news",
  "timestamp": "2025-10-03T12:00:30.564Z",
  "content": {
    "articles": [
      "IslamiCity\n              \n\n\n\n\n            ASK AI\n\t\n      \n\n\n\n\n\n//alert('triggerSearch is just defined.');\n    function triggerSearch() {\n        // submitToChatILM();\n        debugger;\n        //alert('triggerSearch kicked in.');\n        searchValue = window.document.getElementById('searchBox').value;\n        // alert('stopped chatilm searchValue:' + searchValue);\n        // debugger;\n        \n        $html = '<div class=\"align-items-center\" style=\"text-align: center;margin-top:30px;\"><strong>Contacting ChatILM. Please wait....<br></strong><div class=\"spinner-border ms-auto\" role=\"status\" aria-hidden=\"true\" style=\"color:red;display:inline-block;margin-top: 20px;\"></div></div>';\n        $('#results').html($html); \n        /*\n        \n        */\n        // alert('temporarily paused.');\n        // return;\n        const appName = '/ic3'; // Pass your application name as a prefix\n        uuid = getSessionUUID(appName);\n        if ( lastQuestion ){\n            addQuery(appName, lastQuestion + '@@@' + lastAnswer);\n        }\n        const lastFourQueriesString = getLastFourQueriesString(appName);\n        getChatILMResults_STEP2(appName,searchValue,uuid,lastFourQueriesString);            \n        return false;\n        // debugger;\n        if (searchValue) {\n            window.location.href = 'https://chatilm.islamicity.org/?question=' + window.document.getElementById('searchBox').value;\n        } else {\n            //alert('Search box empty. ');\n            return false;\n        }\n        \n    }\n\naskAIButtonIsVisible = false;    \ndocument.addEventListener(\"DOMContentLoaded\", function() {\n\n    \n\n    const searchBox = document.getElementById(\"searchBox\");\n    const goButton = document.getElementById(\"goButton\");\n\n    const questionWords = [\"which\", \"what\", \"where\", \"why\", \"when\", \"who\", \"how\", \"can\", \"is\", \"do\", \"does\", \"will\", \"shall\", \"could\", \"should\", \"would\"];\n\n    function shouldShowGoButton(inputValue, lastKey) {\n        const spaceCount = (inputValue.match(/ /g) || []).length;\n        const firstWord = inputValue.trim().split(/\\s+/)[0].toLowerCase();\n        searchEnabled = false;\n        //document.getElementsByClassName('SongList')[0].innerHTML = '';\n        return spaceCount >= 3 || lastKey === \"?\" || questionWords.includes(firstWord);\n    }\n\n    function showGoButton() {\n        askAIButtonIsVisible = true;\n        goButton.style.visibility = \"visible\";\n        goButton.style.opacity = \"1\";\n        searchEnabled = false;\n        // document.getElementsByClassName('SongList')[0].innerHTML = '';\n        \n    }\n\n    function hideGoButton() {\n        // alert('hide the go button.');\n        askAIButtonIsVisible = false;\n        goButton.style.opacity = \"0\";\n        setTimeout(() => goButton.style.visibility = \"hidden\", 500);\n        searchEnabled = true;\n\n        const songList = document.querySelector('.SongList');\n        songList.innerHTML = '';\n        \n        const results = document.querySelector('#results');\n        results.innerHTML = '';\n        \n        \n    }\n\n    searchBox.addEventListener(\"input\", function(event) {\n        if (shouldShowGoButton(searchBox.value, event.data)) {\n            showGoButton();\n        } else {\n            hideGoButton();\n        }   \n    });\n\n    \n\n    goButton.addEventListener(\"click\", triggerSearch);\n    \n    searchBox.addEventListener(\"keydown\", function(event) {\n        if (event.key === \"Enter\") {\n            event.preventDefault();\n            return false;\n            searchValue = window.document.getElementById('searchBox').value;\n            // debugger;\n            if ( searchValue ) {\n                triggerSearch();\n            } else {\n\n            }\n        }\n    });\n\n    // Expose hideGoButton globally so you can call it anytime\n    window.hideGoButton = hideGoButton;\n});\n\n\n\n\n                ×\n              \n\n              \n\n              \n              \n              \n              \n\n              \n                Advanced options\n                \n                  \n                    \n                    Search in:\n                    \n                      \n                      Title\n                    \n                    \n                      \n                      Authors/Source/By\n                    \n                    \n                      \n                      Category (Apps, Videos, Articles )\n                    \n                     Prefix\n                  \n                   \n                \n                    Search options:\n                    \n                     Fuzzy \n                \n                    \n                  \n                        Combine multiple terms with:\n                         OR\n                         AND",
      "Minnesota AG Keith Ellison Holds News Conference Location: St. Paul, Minnesota, United States Aired: May 30, 2020 | 1:26pm EDT | C-SPAN.org"
    ],
    "headlines": [
      "News Conference: Minnesota AG Keith Ellison",
      "Subscribe to our newsletter",
      "The World's Most Urgent To-Do List is 1,400 Years Old",
      "The Importance of Being Fair & Standing For Justice in Islam",
      "Success In Prophet Muhammad's (PBUH) Revolutionary System"
    ],
    "categories": []
  },
  "metadata": {
    "title": "News Conference: Minnesota AG Keith Ellison",
    "description": "",
    "language": "en-US"
  }
}